univarfem/__init__.py
univarfem/fem.py
univarfem/gaussquad.py
univarfem/mesh.py
univarfem-0.0.2.dist-info/METADATA
univarfem-0.0.2.dist-info/WHEEL
univarfem-0.0.2.dist-info/top_level.txt
univarfem-0.0.2.dist-info/RECORD
